geon_services_core/__init__.py
geon_services_core/api.py
geon_services_core/app.py
geon_services_core/auth.py
geon_services_core/cache.py
geon_services_core/config_models.py
geon_services_core/database.py
geon_services_core/jwt.py
geon_services_core/permissions_reader.py
geon_services_core/runtime_config.py
geon_services_core/tenant_handler.py
geon_services_core/translator.py
geon_services_core-0.6.dist-info/METADATA
geon_services_core-0.6.dist-info/WHEEL
geon_services_core-0.6.dist-info/top_level.txt
geon_services_core-0.6.dist-info/RECORD
