Metadata-Version: 2.1
Name: geon-services-core
Version: 0.6
Summary: A package GEON IT Corp. uses for themselves
Author: Ömer Selçuk Çetin
Author-email: <omerselcukcetin@gmail.com>
Keywords: python,gis,qgis,geon,qwc2
Classifier: Intended Audience :: Developers
Classifier: Programming Language :: Python :: 3
Classifier: Operating System :: Unix
Classifier: Operating System :: MacOS :: MacOS X
Classifier: Operating System :: Microsoft :: Windows
